notion_apilib/__init__.py
notion_apilib/_client/__init__.py
notion_apilib/_client/_api_requests/__init__.py
notion_apilib/_client/_api_requests/_utils/__init__.py
notion_apilib/_client/_api_requests/_utils/header_.py
notion_apilib/_client/_api_requests/_utils/requests_.py
notion_apilib/_client/_api_requests/api/__init__.py
notion_apilib/_client/_api_requests/api/blocks_.py
notion_apilib/_client/_api_requests/api/database_.py
notion_apilib/_client/_api_requests/api/page_.py
notion_apilib/_client/_api_requests/constants/__init__.py
notion_apilib/_client/_api_requests/constants/limits.py
notion_apilib/_client/_api_requests/constants/notion.py
notion_apilib/_client/_api_requests/constants/status_codes.py
notion_apilib/_client/_utils.py
notion_apilib/_client/block_.py
notion_apilib/_client/database_.py
notion_apilib/_client/exceptions_.py
notion_apilib/_client/page_.py
notion_apilib/data/__init__.py
notion_apilib/data/_blocks/__init__.py
notion_apilib/data/_blocks/block.py
notion_apilib/data/_blocks/data/__init__.py
notion_apilib/data/_blocks/data/_children/__init__.py
notion_apilib/data/_blocks/data/_children/child_.py
notion_apilib/data/_blocks/data/_children/heading_.py
notion_apilib/data/_blocks/data/_children/items_.py
notion_apilib/data/_blocks/data/_children/other_.py
notion_apilib/data/_blocks/data/_children/tables_.py
notion_apilib/data/_blocks/data/code_.py
notion_apilib/data/_blocks/data/equation_.py
notion_apilib/data/_blocks/data/link_.py
notion_apilib/data/_blocks/data/other_.py
notion_apilib/data/_blocks/data/resources_.py
notion_apilib/data/_blocks/data/structures/__init__.py
notion_apilib/data/_blocks/factory/__init__.py
notion_apilib/data/_blocks/factory/_children/__init__.py
notion_apilib/data/_blocks/factory/_children/child_.py
notion_apilib/data/_blocks/factory/_children/heading_.py
notion_apilib/data/_blocks/factory/_children/items_.py
notion_apilib/data/_blocks/factory/_children/other_.py
notion_apilib/data/_blocks/factory/_children/tables_.py
notion_apilib-0.0.1a0.dist-info/LICENSE
notion_apilib-0.0.1a0.dist-info/METADATA
notion_apilib-0.0.1a0.dist-info/WHEEL
notion_apilib-0.0.1a0.dist-info/RECORD
