Metadata-Version: 2.1
Name: notion-apilib
Version: 0.0.1a0
Summary: This library allows developers to call Notion API using custom DSL Pydantic-validated classes and API methods
Home-page: https://github.com/Real1tyy/notion-apilib-python
License: MIT
Keywords: notion,api,pydantic,dsl,python
Author: Real1ty
Author-email: vavro.matej3@gmail.com
Requires-Python: >=3.9,<4.0
Classifier: Development Status :: 4 - Beta
Classifier: Intended Audience :: Developers
Classifier: License :: OSI Approved :: MIT License
Classifier: Programming Language :: Python
Classifier: Programming Language :: Python :: 3
Classifier: Programming Language :: Python :: 3.9
Classifier: Programming Language :: Python :: 3.10
Classifier: Programming Language :: Python :: 3.11
Classifier: Programming Language :: Python :: 3.12
Classifier: Topic :: Internet :: WWW/HTTP
Classifier: Topic :: Software Development :: Libraries :: Python Modules
Requires-Dist: anyio (>=4.4.0,<5.0.0)
Requires-Dist: asttokens (==2.4.1)
Requires-Dist: backcall (==0.2.0)
Requires-Dist: beautifulsoup4 (==4.12.3)
Requires-Dist: bleach (==6.1.0)
Requires-Dist: build (==1.2.1)
Requires-Dist: certifi (==2024.7.4)
Requires-Dist: charset-normalizer (==3.3.2)
Requires-Dist: click (==8.1.7)
Requires-Dist: decorator (==5.1.1)
Requires-Dist: defusedxml (==0.7.1)
Requires-Dist: dependency-injector (==4.41.0)
Requires-Dist: dnspython (==2.6.1)
Requires-Dist: docopt (==0.6.2)
Requires-Dist: executing (==2.0.1)
Requires-Dist: fastjsonschema (==2.20.0)
Requires-Dist: greenlet (==3.0.3)
Requires-Dist: h11 (==0.14.0)
Requires-Dist: httpcore (==1.0.5)
Requires-Dist: httpx (==0.27.0)
Requires-Dist: idna (==3.7)
Requires-Dist: jedi (==0.19.1)
Requires-Dist: jinja2 (==3.1.4)
Requires-Dist: jsonschema (==4.22.0)
Requires-Dist: jsonschema-specifications (==2023.12.1)
Requires-Dist: mako (==1.3.5)
Requires-Dist: markupsafe (==2.1.5)
Requires-Dist: matplotlib-inline (==0.1.7)
Requires-Dist: mccabe (==0.7.0)
Requires-Dist: pandocfilters (==1.5.1)
Requires-Dist: parso (==0.8.4)
Requires-Dist: pexpect (==4.9.0)
Requires-Dist: pickleshare (==0.7.5)
Requires-Dist: platformdirs (==4.2.2)
Requires-Dist: prompt-toolkit (==3.0.47)
Requires-Dist: psycopg2 (==2.9.9)
Requires-Dist: ptyprocess (==0.7.0)
Requires-Dist: pycodestyle (==2.12.0)
Requires-Dist: pydantic (>=2.8.2,<3.0.0)
Requires-Dist: pyflakes (==3.2.0)
Requires-Dist: pygments (==2.18.0)
Requires-Dist: pymongo (==4.8.0)
Requires-Dist: pyproject-hooks (==1.1.0)
Requires-Dist: python-dateutil (==2.9.0.post0)
Requires-Dist: python-dotenv (==1.0.1)
Requires-Dist: pyzmq (==26.0.3)
Requires-Dist: referencing (==0.35.1)
Requires-Dist: requests (==2.32.3)
Requires-Dist: returns (==0.23.0)
Requires-Dist: rpds-py (==0.18.1)
Requires-Dist: six (==1.16.0)
Requires-Dist: sniffio (==1.3.1)
Requires-Dist: soupsieve (==2.5)
Requires-Dist: tinycss2 (==1.3.0)
Requires-Dist: tornado (==6.4.1)
Requires-Dist: types-requests (==2.32.0.20240622)
Requires-Dist: typing-extensions (==4.12.2)
Requires-Dist: urllib3 (==2.2.2)
Requires-Dist: wcwidth (==0.2.13)
Requires-Dist: webencodings (==0.5.1)
Project-URL: Documentation, https://github.com/Real1tyy/notion-apilib-python/wiki
Project-URL: Repository, https://github.com/Real1tyy/notion-apilib-python
